sakura/__init__.py
sakura/client/__init__.py
sakura/client/apitools.py
sakura/client/shell.py
sakura/client/apiobject/dataflows.py
sakura/client/apiobject/opclasses.py
sakura/client/apiobject/operators.py
sakura/client/apiobject/parameters.py
sakura/client/apiobject/plugs.py
sakura/client/apiobject/root.py
sakura/common/access.py
sakura/common/bottle.py
sakura/common/cache.py
sakura/common/chunk.py
sakura/common/conf.py
sakura/common/errors.py
sakura/common/events.py
sakura/common/geo.py
sakura/common/io.py
sakura/common/password.py
sakura/common/planner.py
sakura/common/tools.py
sakura/common/types.py
sakura/common/gpu/__init__.py
sakura/common/gpu/libgbm.py
sakura/common/gpu/tools.py
sakura/common/gpu/libegl/__init__.py
sakura/common/gpu/libegl/context.py
sakura/common/gpu/libegl/devices/__init__.py
sakura/common/gpu/libegl/devices/gbm.py
sakura/common/gpu/libegl/devices/generic.py
sakura/common/gpu/openglapp/__init__.py
sakura/common/gpu/openglapp/base.py
sakura/common/gpu/openglapp/eglapp.py
sakura/common/gpu/openglapp/glutapp.py
sakura/common/io/__init__.py
sakura/common/io/api.py
sakura/common/io/const.py
sakura/common/io/debug.py
sakura/common/io/held.py
sakura/common/io/pack.py
sakura/common/io/proxy.py
sakura/common/io/tools.py
sakura/daemon/__init__.py
sakura/daemon/conf.py
sakura/daemon/csvtools.py
sakura/daemon/daemon.py
sakura/daemon/engine.py
sakura/daemon/greenlets.py
sakura/daemon/loading.py
sakura/daemon/tools.py
sakura/daemon/db/column.py
sakura/daemon/db/database.py
sakura/daemon/db/datastore.py
sakura/daemon/db/grants.py
sakura/daemon/db/query.py
sakura/daemon/db/table.py
sakura/daemon/db/adapters/__init__.py
sakura/daemon/db/adapters/native.py
sakura/daemon/db/adapters/undertracks.py
sakura/daemon/db/drivers/__init__.py
sakura/daemon/db/drivers/postgresql.py
sakura/daemon/processing/column.py
sakura/daemon/processing/operator.py
sakura/daemon/processing/parameter.py
sakura_py-0.8.1.dist-info/METADATA
sakura_py-0.8.1.dist-info/RECORD
sakura_py-0.8.1.dist-info/WHEEL
sakura_py-0.8.1.dist-info/entry_points.txt
sakura_py-0.8.1.dist-info/top_level.txt
