Metadata-Version: 2.1
Name: sakura-py
Version: 0.8.1
Summary: Sakura platform installation files.
Home-page: https://github.com/sakura-team/sakura
Author: Etienne Duble
Author-email: etienne.duble@imag.fr
License: BSD
Keywords: sakura data-processing research capitalization
Platform: UNKNOWN
Requires-Dist: cffi
Requires-Dist: gevent
Requires-Dist: gevent-websocket
Requires-Dist: bottle
Requires-Dist: numpy
Requires-Dist: psycopg2-binary
Requires-Dist: pony (==0.7.6)
Requires-Dist: websocket-client
Requires-Dist: pillow-simd
Requires-Dist: cython
Requires-Dist: pyopengl
Requires-Dist: pyopengl-accelerate
Requires-Dist: requests
